elitech/__init__.py
elitech/msg.py
scripts/__init__.py
scripts/elitech_device.py
tests/__init__.py
tests/test_device.py
tests/test_msg.py
elitech_datareader-1.0.5.dist-info/LICENSE
elitech_datareader-1.0.5.dist-info/METADATA
elitech_datareader-1.0.5.dist-info/WHEEL
elitech_datareader-1.0.5.dist-info/dependency_links.txt
elitech_datareader-1.0.5.dist-info/entry_points.txt
elitech_datareader-1.0.5.dist-info/top_level.txt
elitech_datareader-1.0.5.dist-info/RECORD
