Metadata-Version: 2.1
Name: elitech-datareader
Version: 1.0.5
Summary: Elitech rc4 data access tool and library.
Home-page: http://github.com/civic/elitech-datareader/
Author: civic
Author-email: dev@civic-apps.com
License: MIT
Platform: any
Classifier: License :: OSI Approved :: MIT License
Classifier: Programming Language :: Python
Classifier: Programming Language :: Python :: 2
Classifier: Programming Language :: Python :: 2.7
Classifier: Programming Language :: Python :: 3
Classifier: Programming Language :: Python :: 3.4
Classifier: Programming Language :: Python :: 3.5
Classifier: Programming Language :: Python :: 3.6
Classifier: Programming Language :: Python :: 3.7
Classifier: Programming Language :: Python :: 3.8
Classifier: Programming Language :: Python :: 3.9
Classifier: Topic :: Communications
Classifier: Topic :: Software Development :: Libraries
Classifier: Topic :: Software Development :: Libraries :: Python Modules
Requires-Dist: enum34 (==1.1.6)
Requires-Dist: pyserial (==2.7)
Requires-Dist: six (>=1.9.0)
